cgm_format/__init__.py
cgm_format/format_parser.py
cgm_format/format_processor.py
cgm_format/formats/UNIFIED_FORMAT.md
cgm_format/formats/__init__.py
cgm_format/formats/dexcom.json
cgm_format/formats/dexcom.py
cgm_format/formats/libre.json
cgm_format/formats/libre.py
cgm_format/formats/medtronic_WIP.py
cgm_format/formats/unified.json
cgm_format/formats/unified.py
cgm_format/interface/PIPELINE.md
cgm_format/interface/__init__.py
cgm_format/interface/cgm_interface.py
cgm_format/interface/schema.py
cgm_format-0.7.0.dist-info/METADATA
cgm_format-0.7.0.dist-info/WHEEL
cgm_format-0.7.0.dist-info/licenses/LICENSE
cgm_format-0.7.0.dist-info/RECORD
