Metadata-Version: 2.4
Name: cgm-format
Version: 0.7.0
Summary: Unified CGM data format converter for ML training and inference
Author-email: Newton Winter <isoutthere@gmail.com>, Alex Karmazin <karmazinalex@gmail.com>
Maintainer-email: Alex Karmazin <karmazinalex@gmail.com>, Anton Kulaga <antonkulaga@gmail.com>, Newton Winter <isoutthere@gmail.com>
License: MIT License
License-File: LICENSE
Requires-Python: >=3.10
Requires-Dist: polars>=1.34.0
Provides-Extra: dev
Requires-Dist: frictionless>=5.18.1; extra == 'dev'
Requires-Dist: pandas>=2.3.3; extra == 'dev'
Requires-Dist: pyarrow>=21.0.0; extra == 'dev'
Requires-Dist: pytest>=8.0.0; extra == 'dev'
Provides-Extra: extra
Requires-Dist: frictionless>=5.18.1; extra == 'extra'
Requires-Dist: pandas>=2.3.3; extra == 'extra'
Requires-Dist: pyarrow>=21.0.0; extra == 'extra'
